PyCourrier/MailSender.py
PyCourrier/__init__.py
PyCourrier/config.py
PyCourrier/exceptions.py
PyCourrier/utils.py
tests/__init__.py
tests/test_mail_sender.py
tests/test_utils.py
PyCourrier-0.2.2.dist-info/LICENSE
PyCourrier-0.2.2.dist-info/METADATA
PyCourrier-0.2.2.dist-info/WHEEL
PyCourrier-0.2.2.dist-info/top_level.txt
PyCourrier-0.2.2.dist-info/RECORD
